saltext/tidx2/__init__.py
saltext/tidx2/loader.py
saltext/tidx2/version.py
saltext/tidx2/modules/__init__.py
saltext/tidx2/modules/tidx2_mod.py
saltext/tidx2/states/__init__.py
saltext/tidx2/states/tidx2_mod.py
salt_tidx2_extension-2.1.0.dist-info/LICENSE
salt_tidx2_extension-2.1.0.dist-info/METADATA
salt_tidx2_extension-2.1.0.dist-info/WHEEL
salt_tidx2_extension-2.1.0.dist-info/entry_points.txt
salt_tidx2_extension-2.1.0.dist-info/top_level.txt
salt_tidx2_extension-2.1.0.dist-info/RECORD
