Metadata-Version: 2.1
Name: salt-tidx2-extension
Version: 2.1.0
Summary: Test Extension 2 - DO NOT USE IN SALT
Home-page: https://github.com/salt-extensions/salt-ext-test-2
Author: Pedro Algarvio
Author-email: pedro@algarvio.me
License: Apache Software License
Project-URL: Source, https://github.com/salt-extensions/salt-ext-test-2
Project-URL: Tracker, https://github.com/salt-extensions/salt-ext-test-2/issues
Keywords: salt-extension
Platform: any
Classifier: Programming Language :: Python
Classifier: Programming Language :: Cython
Classifier: Programming Language :: Python :: 3
Classifier: Programming Language :: Python :: 3 :: Only
Classifier: Programming Language :: Python :: 3.5
Classifier: Programming Language :: Python :: 3.6
Classifier: Programming Language :: Python :: 3.7
Classifier: Programming Language :: Python :: 3.8
Classifier: Programming Language :: Python :: 3.9
Classifier: Development Status :: 4 - Beta
Classifier: Intended Audience :: Developers
Classifier: License :: OSI Approved :: Apache Software License
Requires-Python: >=3.5
Requires-Dist: salt (>=3001)
Provides-Extra: tests
Requires-Dist: pytest-salt-factories (>=0.95.0) ; extra == 'tests'
